gym_covid19outbreak/__init__.py
gym_covid19outbreak/envs/__init__.py
gym_covid19outbreak/envs/actors.py
gym_covid19outbreak/envs/covid19outbreak.py
gym_covid19outbreak/envs/diseaseOutbreaks.py
gym_covid19outbreak/envs/gameUtils.py
gym_covid19outbreak-0.0.2.dist-info/LICENSE
gym_covid19outbreak-0.0.2.dist-info/METADATA
gym_covid19outbreak-0.0.2.dist-info/WHEEL
gym_covid19outbreak-0.0.2.dist-info/top_level.txt
gym_covid19outbreak-0.0.2.dist-info/RECORD
