Metadata-Version: 2.1
Name: gym-covid19outbreak
Version: 0.0.2
Summary: A OpenAI Gym Env for covid19outbreak
Home-page: https://github.com/batalong123/gym-covid19outbreak
Author: Massock Batalong M.B.
Author-email: lumierebatalong@gmail.com
License: UNKNOWN
Platform: UNKNOWN
Requires-Dist: gym
Requires-Dist: pygame
Requires-Dist: numpy
